{
  "id": "rss-20260606-026",
  "title": "Designing the hf CLI as an agent-optimized way to work with the Hub",
  "source_url": "https://huggingface.co/blog/hf-cli-for-agents",
  "source_type": "rss",
  "summary": "本文介绍了如何将Hugging Face的CLI设计为一种面向AI代理优化的工具，以更高效地与Hub交互。通过简化命令、支持自动化流程和增强可脚本化能力，该设计旨在提升代理在模型、数据集和空间管理等任务中的执行效率。",
  "published_at": "2026-06-06",
  "collected_at": "2026-06-06T04:08:25.046881+00:00",
  "status": "draft",
  "metadata": {
    "feed_name": "Hugging Face Blog",
    "feed_url": "https://huggingface.co/blog/feed.xml"
  },
  "analysis": {
    "score": 7,
    "scoring_reasons": "该设计直接针对AI代理的使用场景优化，提高了自动化操作Hub资源的实用性和效率，对开发和运维有实际帮助，但尚未达到改变格局的突破性程度。",
    "scoring_dimensions": {
      "tech_depth": 6,
      "innovation": 7,
      "usability": 8
    },
    "technical_highlights": [
      "面向AI代理的CLI设计，支持脚本化与自动化",
      "简化Hub交互命令，提升集成效率"
    ]
  },
  "tags": [
    "Hugging Face",
    "CLI",
    "AI代理"
  ]
}